{
    "openapi": "3.0.2",
    "info": {
        "title": "tackle-pathfinder",
        "version": "0.0.4",
        "description": "Tackle PathFinder 0.0.4\n\nChanges : \n* added delete assessment function\n* added create assessment copying responses from another assessment\n* added bulk creation/copy of assessments\n* added identified risks function\n* added assessment confidence function\n* added multilanguage optional param for GetAssessment\n* added get questionnaire header list\n"
    },
    "paths": {
        "/assessments": {
            "summary": "Path used to manage a single assessment.",
            "description": "The REST endpoint/path used to get, update, and delete instances of an `assessment`.  \nThis path contains `GET`, `POST` operations used to perform the get a list of assessments and to create one.",
            "get": {
                "parameters": [
                    {
                        "examples": {
                            "application_null": {
                                "value": ""
                            },
                            "application_noassessed": {
                                "value": "1000"
                            },
                            "application_alreadyassessed": {
                                "value": "1"
                            }
                        },
                        "name": "applicationId",
                        "description": "",
                        "schema": {
                            "type": "integer"
                        },
                        "in": "query"
                    }
                ],
                "responses": {
                    "200": {
                        "content": {
                            "application/json": {
                                "schema": {
                                    "type": "array",
                                    "items": {
                                        "$ref": "#/components/schemas/AssessmentHeader"
                                    }
                                },
                                "examples": {
                                    "application_noassessed": {
                                        "value": [
                                        ]
                                    },
                                    "application_alreadyassessed": {
                                        "value": [
                                            {
                                                "status": "EMPTY",
                                                "applicationId": 68,
                                                "id": 66
                                            }
                                        ]
                                    }
                                }
                            }
                        },
                        "description": "Success"
                    },
                    "400": {
                        "content": {
                            "text/xml": {
                                "examples": {
                                    "application_null": {
                                        "value": ""
                                    }
                                }
                            }
                        },
                        "description": "When the request is not well formed."
                    }
                },
                "operationId": "getApplicationAssessments",
                "description": ""
            },
            "post": {
                "requestBody": {
                    "content": {
                        "application/json": {
                            "schema": {
                                "$ref": "#/components/schemas/Application"
                            },
                            "examples": {
                                "assessment_post_ok": {
                                    "value": {
                                        "applicationId": 92
                                    }
                                }
                            }
                        }
                    },
                    "required": true
                },
                "parameters": [
                    {
                        "examples": {
                            "post_copy_assessment": {
                                "value": "57"
                            }
                        },
                        "name": "fromAssessmentId",
                        "description": "Setting this parameter will make API to create the assessment for the applicationId specified in the body to copy all answers and comments from an already existing assessment.",
                        "schema": {
                            "type": "integer"
                        },
                        "in": "query"
                    }
                ],
                "responses": {
                    "201": {
                        "content": {
                            "application/json": {
                                "schema": {
                                    "$ref": "#/components/schemas/AssessmentHeader"
                                },
                                "examples": {
                                    "assessment_post_ok": {
                                        "value": {
                                            "name": "some text",
                                            "status": "EMPTY",
                                            "applicationId": 92,
                                            "id": 3
                                        }
                                    }
                                }
                            }
                        },
                        "description": "Created"
                    },
                    "400": {
                        "description": "Invalid format"
                    },
                    "404": {
                        "description": "If the fromAssessmentId param is passed but that assessment can not be found."
                    }
                },
                "operationId": "createAssessment",
                "summary": "Creates an assessment associated to an applicationId. It can copy the responses from another assessment."
            }
        },
        "/assessments/{assessmentId}": {
            "get": {
                "parameters": [
                    {
                        "name": "language",
                        "description": "ISO language code for the response\nIf not specified the language used will be the original language of the questionnaire",
                        "schema": {
                            "type": "string"
                        },
                        "in": "query"
                    }
                ],
                "responses": {
                    "200": {
                        "content": {
                            "application/json": {
                                "schema": {
                                    "$ref": "#/components/schemas/Get_Assessment"
                                },
                                "examples": {
                                    "Get_Assessment_OK": {
                                        "value": {
                                            "id": 40,
                                            "applicationId": 35,
                                            "status": "COMPLETED",
                                            "stakeholders": [
                                                36,
                                                86
                                            ],
                                            "stakeholderGroups": [
                                                31,
                                                73
                                            ],
                                            "questionnaire": {
                                                "categories": [
                                                    {
                                                        "id": 72,
                                                        "order": 19,
                                                        "title": "some text",
                                                        "questions": [
                                                            {
                                                                "id": 1,
                                                                "order": 84,
                                                                "question": "some text",
                                                                "options": [
                                                                    {
                                                                        "id": 85,
                                                                        "order": 77,
                                                                        "option": "some text",
                                                                        "checked": true
                                                                    },
                                                                    {
                                                                        "id": 16,
                                                                        "order": 88,
                                                                        "option": "some text",
                                                                        "checked": true
                                                                    }
                                                                ],
                                                                "description": "some text"
                                                            },
                                                            {
                                                                "id": 19,
                                                                "order": 30,
                                                                "question": "some text",
                                                                "options": [
                                                                    {
                                                                        "id": 45,
                                                                        "order": 36,
                                                                        "option": "some text",
                                                                        "checked": true
                                                                    },
                                                                    {
                                                                        "id": 37,
                                                                        "order": 57,
                                                                        "option": "some text",
                                                                        "checked": true
                                                                    }
                                                                ],
                                                                "description": "some text"
                                                            }
                                                        ],
                                                        "comment": "some text"
                                                    },
                                                    {
                                                        "id": 74,
                                                        "order": 9,
                                                        "title": "some text",
                                                        "questions": [
                                                            {
                                                                "id": 85,
                                                                "order": 21,
                                                                "question": "some text",
                                                                "options": [
                                                                    {
                                                                        "id": 79,
                                                                        "order": 3,
                                                                        "option": "some text",
                                                                        "checked": true
                                                                    },
                                                                    {
                                                                        "id": 7,
                                                                        "order": 65,
                                                                        "option": "some text",
                                                                        "checked": false
                                                                    }
                                                                ],
                                                                "description": "some text"
                                                            },
                                                            {
                                                                "id": 19,
                                                                "order": 33,
                                                                "question": "some text",
                                                                "options": [
                                                                    {
                                                                        "id": 62,
                                                                        "order": 32,
                                                                        "option": "some text",
                                                                        "checked": true
                                                                    },
                                                                    {
                                                                        "id": 66,
                                                                        "order": 98,
                                                                        "option": "some text",
                                                                        "checked": true
                                                                    }
                                                                ],
                                                                "description": "some text"
                                                            }
                                                        ],
                                                        "comment": "some text"
                                                    }
                                                ],
                                                "title": "some text",
                                                "description": "some text",
                                                "language": "some text"
                                            }
                                        }
                                    }
                                }
                            }
                        },
                        "description": "Successfull response"
                    }
                }
            },
            "delete": {
                "responses": {
                    "204": {
                        "description": "If the assessment gets deleted successfully"
                    },
                    "400": {
                        "description": "If the delete operation failed"
                    },
                    "404": {
                        "description": "If the assessment to be deleted doesn't exist"
                    }
                },
                "summary": "Deletes an assessment",
                "description": "Checks if an assessment exists and deletes it."
            },
            "patch": {
                "requestBody": {
                    "content": {
                        "application/json": {
                            "schema": {
                                "$ref": "#/components/schemas/Pach_Assessment"
                            },
                            "examples": {
                                "path_assessment_rq_body": {
                                    "value": {
                                        "status": "STARTED",
                                        "stakeholders": [
                                            4,
                                            93
                                        ],
                                        "stakeholdersgroups": [
                                            63,
                                            63
                                        ],
                                        "questionnaire": {
                                            "categories": [
                                                {
                                                    "questions": [
                                                        {
                                                            "id": 51,
                                                            "options": [
                                                                {
                                                                    "id": 31,
                                                                    "selected": true
                                                                },
                                                                {
                                                                    "id": 67,
                                                                    "selected": true
                                                                }
                                                            ]
                                                        },
                                                        {
                                                            "id": 47,
                                                            "options": [
                                                                {
                                                                    "id": 43,
                                                                    "selected": true
                                                                },
                                                                {
                                                                    "id": 99,
                                                                    "selected": true
                                                                }
                                                            ]
                                                        }
                                                    ],
                                                    "id": 97,
                                                    "comment": "some text"
                                                },
                                                {
                                                    "questions": [
                                                        {
                                                            "id": 18,
                                                            "options": [
                                                                {
                                                                    "id": 25,
                                                                    "selected": true
                                                                },
                                                                {
                                                                    "id": 58,
                                                                    "selected": true
                                                                }
                                                            ]
                                                        },
                                                        {
                                                            "id": 0,
                                                            "options": [
                                                                {
                                                                    "id": 91,
                                                                    "selected": true
                                                                },
                                                                {
                                                                    "id": 90,
                                                                    "selected": true
                                                                }
                                                            ]
                                                        }
                                                    ],
                                                    "id": 52,
                                                    "comment": "some text"
                                                }
                                            ]
                                        }
                                    }
                                }
                            }
                        }
                    },
                    "required": true
                },
                "responses": {
                    "200": {
                        "content": {
                            "application/json": {
                                "schema": {
                                    "$ref": "#/components/schemas/AssessmentHeader"
                                },
                                "examples": {
                                    "path_assessment_rs_200_body": {
                                        "value": {
                                            "status": "STARTED",
                                            "applicationId": 36,
                                            "id": 79
                                        }
                                    }
                                }
                            }
                        },
                        "description": "when the update has been successful"
                    },
                    "400": {
                        "description": "When the body content is somehow incorrect : wrong ids, wrong values."
                    },
                    "404": {
                        "description": "When the assessment can not be found"
                    }
                },
                "summary": "This operation will update the current Assessment using the assessmentId on the pathparam.",
                "description": "This operation will only consider the assessmentId specified in the pathparam to find the related Assessment.\n\nUpdatable values :\n* status\n* stakeholders\n* stakeholderGroups\n* questionnaire.category.comment\n* questionnaire.category.question.option.checked\n\nOnly the information != null will be considered and modified. The rest will remain untouched."
            },
            "parameters": [
                {
                    "examples": {
                        "get_assessment_assessmentid": {
                            "value": "92"
                        }
                    },
                    "name": "assessmentId",
                    "schema": {
                        "type": "integer"
                    },
                    "in": "path",
                    "required": true
                }
            ]
        },
        "/assessments/bulk": {
            "post": {
                "requestBody": {
                    "content": {
                        "application/json": {
                            "schema": {
                                "type": "array",
                                "items": {
                                    "type": "integer"
                                }
                            },
                            "examples": {
                                "bulk_request": {
                                    "value": [
                                        74,
                                        54
                                    ]
                                }
                            }
                        }
                    },
                    "required": true
                },
                "parameters": [
                    {
                        "name": "fromAssessmentId",
                        "description": "",
                        "schema": {
                            "type": "integer"
                        },
                        "in": "query",
                        "required": false
                    }
                ],
                "responses": {
                    "200": {
                        "content": {
                            "application/json": {
                                "schema": {
                                    "$ref": "#/components/schemas/AssessmentBulk"
                                },
                                "examples": {
                                    "assessment_bulk_post": {
                                        "value": {
                                            "bulkId": 58,
                                            "applications": [
                                                9,
                                                45
                                            ],
                                            "fromAssessmentId": 74,
                                            "createdAssessments": [
                                                {
                                                    "status": "COMPLETE",
                                                    "applicationId": 57,
                                                    "id": 50,
                                                    "error": "some text"
                                                },
                                                {
                                                    "status": "STARTED",
                                                    "applicationId": 6,
                                                    "id": 13,
                                                    "error": "some text"
                                                }
                                            ]
                                        }
                                    }
                                }
                            }
                        },
                        "description": "When the operation finishes successfully."
                    }
                },
                "operationId": "bulkCreateAssessment",
                "summary": "Async call to create a list of assessments for the given applications.",
                "description": "It will allow to copy the assessment answers from a given assessment ( in query params )"
            }
        },
        "/assessments/bulk/{bulkId}": {
            "get": {
                "responses": {
                    "200": {
                        "content": {
                            "application/json": {
                                "schema": {
                                    "$ref": "#/components/schemas/AssessmentBulk"
                                },
                                "examples": {
                                    "bulk_response_ok": {
                                        "value": {
                                            "bulkId": 31,
                                            "applications": [
                                                92,
                                                0
                                            ],
                                            "fromAssessmentId": 72,
                                            "createdAssessments": [
                                                {
                                                    "status": "STARTED",
                                                    "applicationId": 90,
                                                    "id": 52,
                                                    "error": "some text"
                                                },
                                                {
                                                    "status": "COMPLETE",
                                                    "applicationId": 28,
                                                    "id": 18,
                                                    "error": "some text"
                                                }
                                            ]
                                        }
                                    }
                                }
                            }
                        },
                        "description": "If bulk process is found"
                    },
                    "404": {
                        "description": "If bulk process is not found"
                    }
                }
            },
            "parameters": [
                {
                    "name": "bulkId",
                    "schema": {
                        "type": "integer"
                    },
                    "in": "path",
                    "required": true
                }
            ]
        },
        "/assessments/risks": {
            "summary": "Will retrieve the risks for filtered assessments",
            "description": "The response will contain only those applications assessed. This can end on having 0 elements in the response.",
            "post": {
                "requestBody": {
                    "content": {
                        "application/json": {
                            "schema": {
                                "type": "array",
                                "items": {
                                    "$ref": "#/components/schemas/Application"
                                }
                            },
                            "examples": {
                                "risks_ok": {
                                    "value": [
                                        {
                                            "applicationId": 90
                                        },
                                        {
                                            "applicationId": 3
                                        }
                                    ]
                                }
                            }
                        }
                    },
                    "required": true
                },
                "responses": {
                    "200": {
                        "content": {
                            "application/json": {
                                "schema": {
                                    "type": "array",
                                    "items": {
                                        "$ref": "#/components/schemas/RiskLine"
                                    }
                                },
                                "examples": {
                                    "risks_response_ok": {
                                        "value": [
                                            {
                                                "category": "some text",
                                                "question": "some text",
                                                "answer": "some text",
                                                "applications": [
                                                    11,
                                                    72
                                                ]
                                            },
                                            {
                                                "category": "some text",
                                                "question": "some text",
                                                "answer": "some text",
                                                "applications": [
                                                    53,
                                                    44
                                                ]
                                            }
                                        ]
                                    }
                                }
                            }
                        },
                        "description": "Success"
                    }
                }
            }
        },
        "/assessments/confidence": {
            "post": {
                "requestBody": {
                    "content": {
                        "application/json": {
                            "schema": {
                                "type": "array",
                                "items": {
                                    "$ref": "#/components/schemas/Application"
                                }
                            },
                            "examples": {
                                "post_confidence_request": {
                                    "value": [
                                        {
                                            "applicationId": 5
                                        },
                                        {
                                            "applicationId": 51
                                        }
                                    ]
                                }
                            }
                        }
                    },
                    "required": true
                },
                "responses": {
                    "200": {
                        "content": {
                            "application/json": {
                                "schema": {
                                    "type": "array",
                                    "items": {
                                        "$ref": "#/components/schemas/AssessmentConfidence"
                                    }
                                },
                                "examples": {
                                    "confidence_response_ok": {
                                        "value": [
                                            {
                                                "assessmentId": 48,
                                                "confidence": 83
                                            },
                                            {
                                                "assessmentId": 80,
                                                "confidence": 10
                                            }
                                        ]
                                    }
                                }
                            }
                        },
                        "description": "On success"
                    }
                }
            }
        },
        "/assessments/assessment-risk": {
            "post": {
                "requestBody": {
                    "content": {
                        "application/json": {
                            "schema": {
                                "type": "array",
                                "items": {
                                    "$ref": "#/components/schemas/Application"
                                }
                            },
                            "examples": {
                                "assessment-risk-ok": {
                                    "value": [
                                        {
                                            "applicationId": 5
                                        },
                                        {
                                            "applicationId": 37
                                        }
                                    ]
                                }
                            }
                        }
                    },
                    "required": true
                },
                "responses": {
                    "200": {
                        "content": {
                            "application/json": {
                                "schema": {
                                    "type": "array",
                                    "items": {
                                        "$ref": "#/components/schemas/AssessmentRisk"
                                    }
                                },
                                "examples": {
                                    "assessment-risk-ok-resp": {
                                        "value": [
                                            {
                                                "assessmentId": 34,
                                                "risk": "RED"
                                            },
                                            {
                                                "assessmentId": 69,
                                                "risk": "UNKNOWN"
                                            }
                                        ]
                                    }
                                }
                            }
                        },
                        "description": "Success response"
                    }
                }
            }
        },
        "/questionnaires": {
            "get": {
                "parameters": [
                    {
                        "name": "language",
                        "description": "",
                        "schema": {
                            "type": "string"
                        },
                        "in": "query"
                    }
                ],
                "responses": {
                    "200": {
                        "content": {
                            "application/json": {
                                "schema": {
                                    "type": "array",
                                    "items": {
                                        "$ref": "#/components/schemas/QuestionnaireHeader"
                                    }
                                },
                                "examples": {
                                    "success_questionnaireheader": {
                                        "value": [
                                            {
                                                "id": 9,
                                                "name": "some text",
                                                "language": "some text"
                                            },
                                            {
                                                "id": 84,
                                                "name": "some text",
                                                "language": "some text"
                                            }
                                        ]
                                    }
                                }
                            }
                        },
                        "description": "Success"
                    }
                }
            }
        }
    },
    "components": {
        "schemas": {
            "Application": {
                "description": "",
                "required": [
                    "applicationId"
                ],
                "type": "object",
                "properties": {
                    "applicationId": {
                        "description": "",
                        "type": "integer"
                    }
                }
            },
            "AssessmentHeader": {
                "description": "",
                "required": [
                    "id",
                    "applicationId",
                    "status"
                ],
                "type": "object",
                "properties": {
                    "status": {
                        "$ref": "#/components/schemas/Status",
                        "description": ""
                    },
                    "applicationId": {
                        "description": "",
                        "type": "integer"
                    },
                    "id": {
                        "description": "",
                        "type": "integer"
                    }
                },
                "example": {
                    "status": "STARTED",
                    "id": 24,
                    "applicationId": 14
                }
            },
            "Get_Assessment": {
                "title": "Root Type for assessment",
                "description": "The application's assessment",
                "required": [
                    "id",
                    "questionnaire"
                ],
                "type": "object",
                "properties": {
                    "id": {
                        "description": "Assessment id",
                        "type": "integer"
                    },
                    "applicationId": {
                        "description": "Application id",
                        "type": "integer"
                    },
                    "status": {
                        "$ref": "#/components/schemas/Status",
                        "description": "Current status of the assessment"
                    },
                    "stakeholders": {
                        "description": "List of ids of stakeholders",
                        "type": "array",
                        "items": {
                            "type": "integer"
                        }
                    },
                    "stakeholderGroups": {
                        "description": "List of ids of stakeholder groups",
                        "type": "array",
                        "items": {
                            "type": "integer"
                        }
                    },
                    "questionnaire": {
                        "$ref": "#/components/schemas/Get_Questionnaire",
                        "description": "Questionnaire content",
                        "properties": {
                            "title": {
                                "type": "string"
                            },
                            "description": {
                                "type": "string"
                            },
                            "language": {
                                "type": "string"
                            },
                            "sections": {
                                "type": "array",
                                "items": {
                                    "type": "object",
                                    "properties": {
                                        "id": {
                                            "format": "int32",
                                            "type": "integer"
                                        },
                                        "order": {
                                            "format": "int32",
                                            "type": "integer"
                                        },
                                        "title": {
                                            "type": "string"
                                        },
                                        "questions": {
                                            "type": "array",
                                            "items": {
                                                "type": "object",
                                                "properties": {
                                                    "id": {
                                                        "format": "int32",
                                                        "type": "integer"
                                                    },
                                                    "order": {
                                                        "format": "int32",
                                                        "type": "integer"
                                                    },
                                                    "question": {
                                                        "type": "string"
                                                    },
                                                    "description": {
                                                        "type": "string"
                                                    },
                                                    "variant": {
                                                        "type": "string"
                                                    },
                                                    "options": {
                                                        "type": "array",
                                                        "items": {
                                                            "type": "object",
                                                            "properties": {
                                                                "id": {
                                                                    "format": "int32",
                                                                    "type": "integer"
                                                                },
                                                                "order": {
                                                                    "format": "int32",
                                                                    "type": "integer"
                                                                },
                                                                "answer": {
                                                                    "type": "string"
                                                                },
                                                                "checked": {
                                                                    "type": "boolean"
                                                                }
                                                            }
                                                        }
                                                    }
                                                }
                                            }
                                        }
                                    }
                                }
                            }
                        }
                    }
                },
                "example": {
                    "id": 1,
                    "applicationId": 2,
                    "status": "notStarted | inProgress | completed",
                    "stakeholders": [
                        1,
                        2,
                        3
                    ],
                    "stakeholderGroups": [
                        1,
                        2
                    ],
                    "questionnaire": {
                        "title": "Questionnaire #1",
                        "description": "This questionnaire is for...",
                        "language": "en",
                        "sections": [
                            {
                                "id": 1,
                                "order": 0,
                                "title": "General questions",
                                "questions": [
                                    {
                                        "id": 1,
                                        "order": 0,
                                        "question": "What's you favorite movie?",
                                        "description": "This represents a multiple option choice",
                                        "variant": "checkbox",
                                        "options": [
                                            {
                                                "id": 1,
                                                "order": 0,
                                                "answer": "Titanic",
                                                "checked": true
                                            },
                                            {
                                                "id": 2,
                                                "order": 1,
                                                "answer": "Start war",
                                                "checked": false
                                            },
                                            {
                                                "id": 3,
                                                "order": 2,
                                                "answer": "Dr. Strange",
                                                "checked": true
                                            }
                                        ]
                                    },
                                    {
                                        "id": 2,
                                        "order": 1,
                                        "question": "How old are you?",
                                        "description": "This represents a single option choice",
                                        "type": "radioButton",
                                        "options": [
                                            {
                                                "id": 4,
                                                "order": 0,
                                                "answer": "I'm younger than 30",
                                                "checked": true
                                            },
                                            {
                                                "id": 5,
                                                "order": 1,
                                                "answer": "I'm older than 30",
                                                "checked": false
                                            },
                                            {
                                                "id": 6,
                                                "order": 2,
                                                "answer": "I'm too old to tell you",
                                                "checked": false
                                            }
                                        ]
                                    },
                                    {
                                        "id": 3,
                                        "order": 0,
                                        "question": "What is your name?",
                                        "description": "This represents an inputText",
                                        "type": "inputText",
                                        "textValue": "Gabriel Garca Mrquez"
                                    }
                                ]
                            }
                        ]
                    }
                }
            },
            "Get_Category": {
                "title": "Root Type for section",
                "description": "Questionnaire section",
                "required": [
                    "id",
                    "order",
                    "title",
                    "questions"
                ],
                "type": "object",
                "properties": {
                    "id": {
                        "description": "DB id",
                        "type": "integer"
                    },
                    "order": {
                        "description": "Used for sorting multiple sections",
                        "type": "integer"
                    },
                    "title": {
                        "description": "Title of the section. This will be represented as a Wizard's section",
                        "type": "string"
                    },
                    "questions": {
                        "description": "List of questions that belongs to this section",
                        "type": "array",
                        "items": {
                            "$ref": "#/components/schemas/Get_Question"
                        }
                    },
                    "comment": {
                        "description": "Comment from the user to the category",
                        "type": "string"
                    }
                },
                "example": {
                    "id": 98,
                    "order": 9,
                    "title": "some text",
                    "questions": [
                        {
                            "id": 35,
                            "order": 78,
                            "question": "some text",
                            "options": [
                                {
                                    "id": 82,
                                    "order": 58,
                                    "option": "some text",
                                    "checked": true
                                },
                                {
                                    "id": 32,
                                    "order": 99,
                                    "option": "some text",
                                    "checked": true
                                }
                            ],
                            "description": "some text"
                        },
                        {
                            "id": 77,
                            "order": 78,
                            "question": "some text",
                            "options": [
                                {
                                    "id": 96,
                                    "order": 53,
                                    "option": "some text",
                                    "checked": true
                                },
                                {
                                    "id": 25,
                                    "order": 18,
                                    "option": "some text",
                                    "checked": true
                                }
                            ],
                            "description": "some text"
                        }
                    ],
                    "comment": "some text"
                }
            },
            "Get_Question": {
                "title": "Root Type for question",
                "description": "A question",
                "required": [
                    "id",
                    "order",
                    "question",
                    "options"
                ],
                "type": "object",
                "properties": {
                    "id": {
                        "description": "DB id",
                        "type": "integer"
                    },
                    "order": {
                        "description": "Used for sorting multiple questions",
                        "type": "integer"
                    },
                    "question": {
                        "description": "Question's value typically ends with '?'",
                        "type": "string"
                    },
                    "options": {
                        "description": "List of possible answers to the question. Applicable if variant=checkbox|radioButton.",
                        "type": "array",
                        "items": {
                            "$ref": "#/components/schemas/Get_QuestionOption"
                        }
                    },
                    "description": {
                        "description": "Extra info. This will appear in the tooltip",
                        "type": "string"
                    }
                },
                "example": {
                    "id": 1,
                    "order": 0,
                    "question": "What's you favorite movie?",
                    "description": "This represents a multiple option choice",
                    "variant": "checkbox",
                    "options": [
                        {
                            "id": 1,
                            "order": 0,
                            "option": "Titanic",
                            "checked": true
                        },
                        {
                            "id": 2,
                            "order": 1,
                            "option": "Start war",
                            "checked": false
                        },
                        {
                            "id": 3,
                            "order": 2,
                            "option": "Dr. Strange",
                            "checked": true
                        }
                    ]
                }
            },
            "Get_QuestionOption": {
                "title": "Root Type for question_option",
                "description": "A possible question's answer typically represented in a RadioButton",
                "required": [
                    "checked",
                    "id",
                    "option",
                    "order",
                    "risk"
                ],
                "type": "object",
                "properties": {
                    "id": {
                        "description": "The DB id",
                        "type": "integer"
                    },
                    "order": {
                        "description": "For sorting multiple radioButtons/checkboxes",
                        "type": "integer"
                    },
                    "option": {
                        "description": "The radioButton/checkbox text",
                        "type": "string"
                    },
                    "checked": {
                        "description": "Whether or not this option was selected by the user",
                        "type": "boolean"
                    },
                    "risk": {
                        "description": "",
                        "enum": [
                            "GREEN",
                            "AMBER",
                            "RED"
                        ],
                        "type": "string"
                    }
                },
                "example": {
                    "id": 77,
                    "order": 80,
                    "option": "some text",
                    "checked": true,
                    "risk": "AMBER"
                }
            },
            "Pach_Assessment": {
                "description": "",
                "required": [
                ],
                "type": "object",
                "properties": {
                    "status": {
                        "$ref": "#/components/schemas/Status",
                        "description": ""
                    },
                    "stakeholders": {
                        "description": "",
                        "type": "array",
                        "items": {
                            "type": "integer"
                        }
                    },
                    "stakeholdersgroups": {
                        "description": "",
                        "type": "array",
                        "items": {
                            "type": "integer"
                        }
                    },
                    "questionnaire": {
                        "$ref": "#/components/schemas/Patch_Questionnaire",
                        "description": ""
                    }
                }
            },
            "Get_Questionnaire": {
                "description": "",
                "required": [
                    "categories",
                    "title",
                    "language"
                ],
                "type": "object",
                "properties": {
                    "categories": {
                        "description": "",
                        "type": "array",
                        "items": {
                            "$ref": "#/components/schemas/Get_Category"
                        }
                    },
                    "title": {
                        "description": "",
                        "type": "string"
                    },
                    "description": {
                        "description": "",
                        "type": "string"
                    },
                    "language": {
                        "description": "",
                        "type": "string"
                    }
                }
            },
            "Patch_Questionnaire": {
                "description": "",
                "type": "object",
                "properties": {
                    "categories": {
                        "description": "",
                        "type": "array",
                        "items": {
                            "$ref": "#/components/schemas/Patch_Category"
                        }
                    }
                }
            },
            "Patch_Category": {
                "description": "",
                "required": [
                    "id"
                ],
                "type": "object",
                "properties": {
                    "questions": {
                        "description": "",
                        "type": "array",
                        "items": {
                            "$ref": "#/components/schemas/Patch_Question"
                        }
                    },
                    "id": {
                        "description": "",
                        "type": "integer"
                    },
                    "comment": {
                        "description": "",
                        "type": "string"
                    }
                }
            },
            "Patch_Question": {
                "description": "",
                "required": [
                    "id"
                ],
                "type": "object",
                "properties": {
                    "id": {
                        "description": "",
                        "type": "integer"
                    },
                    "options": {
                        "description": "",
                        "type": "array",
                        "items": {
                            "$ref": "#/components/schemas/Patch_QuestionOption"
                        }
                    }
                }
            },
            "Patch_QuestionOption": {
                "description": "",
                "required": [
                    "id",
                    "selected"
                ],
                "type": "object",
                "properties": {
                    "id": {
                        "description": "",
                        "type": "integer"
                    },
                    "selected": {
                        "description": "",
                        "type": "boolean"
                    }
                }
            },
            "Status": {
                "description": "Status of an Assessment",
                "enum": [
                    "STARTED",
                    "COMPLETE"
                ],
                "type": "string"
            },
            "Post_AssessmentBulk": {
                "description": "",
                "required": [
                    "applications"
                ],
                "type": "object",
                "properties": {
                    "fromAssessmentId": {
                        "description": "",
                        "type": "integer"
                    },
                    "applications": {
                        "description": "",
                        "type": "array",
                        "items": {
                            "$ref": "#/components/schemas/Application"
                        }
                    }
                }
            },
            "AssessmentBulk": {
                "description": "",
                "required": [
                    "bulkId",
                    "applications",
                    "assessments",
                    "completed"
                ],
                "type": "object",
                "properties": {
                    "bulkId": {
                        "description": "",
                        "type": "integer"
                    },
                    "applications": {
                        "description": "",
                        "type": "array",
                        "items": {
                            "type": "integer"
                        }
                    },
                    "fromAssessmentId": {
                        "description": "",
                        "type": "integer"
                    },
                    "completed": {
                        "description": "",
                        "type": "boolean"
                    },
                    "assessments": {
                        "description": "",
                        "type": "array",
                        "items": {
                            "$ref": "#/components/schemas/AssessmentHeaderBulk"
                        }
                    }
                }
            },
            "AssessmentHeaderBulk": {
                "description": "",
                "required": [
                    "id",
                    "applicationId",
                    "status"
                ],
                "type": "object",
                "properties": {
                    "status": {
                        "$ref": "#/components/schemas/Status",
                        "description": ""
                    },
                    "applicationId": {
                        "description": "",
                        "type": "integer"
                    },
                    "id": {
                        "description": "",
                        "type": "integer"
                    },
                    "error": {
                        "description": "",
                        "type": "string"
                    }
                },
                "example": {
                    "status": "STARTED",
                    "id": 24,
                    "applicationId": 14
                }
            },
            "AssessmentBulkPost": {
                "description": "",
                "required": [
                    "applications"
                ],
                "type": "object",
                "properties": {
                    "fromAssessmentId": {
                        "description": "",
                        "type": "integer"
                    },
                    "applications": {
                        "description": "",
                        "type": "array",
                        "items": {
                            "$ref": "#/components/schemas/Application"
                        }
                    }
                }
            },
            "RiskLine": {
                "description": "",
                "required": [
                    "category",
                    "question",
                    "answer",
                    "applications"
                ],
                "type": "object",
                "properties": {
                    "category": {
                        "description": "",
                        "type": "string"
                    },
                    "question": {
                        "description": "",
                        "type": "string"
                    },
                    "answer": {
                        "description": "",
                        "type": "string"
                    },
                    "applications": {
                        "description": "",
                        "type": "array",
                        "items": {
                            "type": "integer"
                        }
                    }
                }
            },
            "AssessmentConfidence": {
                "description": "",
                "required": [
                    "assessmentId",
                    "confidence",
                    "applicationId"
                ],
                "type": "object",
                "properties": {
                    "assessmentId": {
                        "description": "",
                        "type": "integer"
                    },
                    "confidence": {
                        "description": "",
                        "type": "integer"
                    },
                    "applicationId": {
                        "description": "",
                        "type": "integer"
                    }
                }
            },
            "Landscape": {
                "description": "",
                "required": [
                    "assessmentId",
                    "risk"
                ],
                "type": "object",
                "properties": {
                    "assessmentId": {
                        "description": "",
                        "type": "integer"
                    },
                    "risk": {
                        "$ref": "#/components/schemas/RiskLine",
                        "description": ""
                    }
                }
            },
            "Risk": {
                "description": "",
                "enum": [
                    "RED",
                    "AMBER",
                    "GREEN",
                    "UNKNOWN"
                ],
                "type": "string"
            },
            "AssessmentRisk": {
                "description": "",
                "required": [
                    "assessmentId",
                    "risk"
                ],
                "type": "object",
                "properties": {
                    "assessmentId": {
                        "description": "",
                        "type": "integer"
                    },
                    "risk": {
                        "$ref": "#/components/schemas/Risk",
                        "description": ""
                    }
                }
            },
            "QuestionnaireHeader": {
                "description": "",
                "required": [
                    "id",
                    "name",
                    "language"
                ],
                "type": "object",
                "properties": {
                    "id": {
                        "description": "",
                        "type": "integer"
                    },
                    "name": {
                        "description": "",
                        "type": "string"
                    },
                    "language": {
                        "description": "",
                        "type": "string"
                    }
                }
            }
        },
        "responses": {
            "404_ERROR": {
                "content": {
                    "application/json": {

                    }
                },
                "description": ""
            }
        }
    }
}